{"analyzedAt":"2021-08-14T20:18:26.551Z","collected":{"metadata":{"name":"madge","scope":"unscoped","version":"5.0.1","description":"Create graphs from module dependencies.","keywords":["ES6","ES7","AMD","RequireJS","require","module","circular","dependency","dependencies","graphviz","graph"],"date":"2021-06-23T18:20:38.854Z","author":{"name":"Patrik Henningsson","email":"patrik.henningsson@gmail.com","username":"pahen"},"publisher":{"username":"pahen","email":"patrik.henningsson@gmail.com"},"maintainers":[{"username":"pahen","email":"patrik.henningsson@gmail.com"}],"repository":{"type":"git","url":"git://github.com/pahen/madge.git"},"links":{"npm":"https://www.npmjs.com/package/madge","homepage":"https://github.com/pahen/madge","repository":"https://github.com/pahen/madge","bugs":"https://github.com/pahen/madge/issues"},"license":"MIT","dependencies":{"chalk":"^4.1.1","commander":"^7.2.0","commondir":"^1.0.1","debug":"^4.3.1","dependency-tree":"^8.1.1","detective-amd":"^3.1.0","detective-cjs":"^3.1.1","detective-es6":"^2.2.0","detective-less":"^1.0.2","detective-postcss":"^5.0.0","detective-sass":"^3.0.1","detective-scss":"^2.0.1","detective-stylus":"^1.0.0","detective-typescript":"^7.0.0","graphviz":"0.0.9","ora":"^5.4.1","pluralize":"^8.0.0","precinct":"^8.1.0","pretty-ms":"^7.0.1","rc":"^1.2.7","typescript":"^3.9.5","walkdir":"^0.4.1"},"devDependencies":{"@aptoma/eslint-config":"^7.0.1","eslint":"^7.29.0","mocha":"^9.0.1","mz":"^2.7.0","should":"^13.2.3"},"releases":[{"from":"2021-07-15T00:00:00.000Z","to":"2021-08-14T00:00:00.000Z","count":0},{"from":"2021-05-16T00:00:00.000Z","to":"2021-08-14T00:00:00.000Z","count":3},{"from":"2021-02-15T00:00:00.000Z","to":"2021-08-14T00:00:00.000Z","count":5},{"from":"2020-08-14T00:00:00.000Z","to":"2021-08-14T00:00:00.000Z","count":9},{"from":"2019-08-15T00:00:00.000Z","to":"2021-08-14T00:00:00.000Z","count":17}],"hasTestScript":true,"readme":"<p align=\"center\">\n\t<img alt=\"madge\" src=\"http://pahen.github.io/madge/logo.svg\" width=\"320\">\n</p>\n\n<p align=\"center\">\n\t<img alt=\"Last version\" src=\"https://img.shields.io/github/tag/pahen/madge.svg?style=flat-square\" />\n\t<a href=\"https://travis-ci.com/pahen/madge\">\n\t\t<img alt=\"Build Status\" src=\"http://img.shields.io/travis/pahen/madge/master.svg?style=flat-square\" />\n\t</a>\n\t<a href=\"https://david-dm.org/pahen/madge\">\n\t\t<img alt=\"Dependency status\" src=\"http://img.shields.io/david/pahen/madge.svg?style=flat-square\" />\n\t</a>\n\t<a href=\"https://david-dm.org/pahen/madge#info=devDependencies\">\n\t\t<img alg=\"Dev Dependencies status\" src=\"http://img.shields.io/david/dev/pahen/madge.svg?style=flat-square\" />\n\t</a>\n\t<a href=\"https://www.npmjs.org/package/madge\">\n\t\t<img alg=\"NPM Status\" src=\"http://img.shields.io/npm/dm/madge.svg?style=flat-square\" />\n\t</a>\n\t<a href=\"https://paypal.me/pahen\" target=\"_blank\">\n\t\t<img alt=\"Donate\" src=\"https://img.shields.io/badge/donate-paypal-blue.svg?style=flat-square\" />\n\t</a>\n</p>\n\n\n**Madge** is a developer tool for generating a visual graph of your module dependencies, finding circular dependencies, and give you other useful info. Joel Kemp's awesome [dependency-tree](https://github.com/mrjoelkemp/node-dependency-tree) is used for extracting the dependency tree.\n\n\n* Works for JavaScript (AMD, CommonJS, and ES6 modules)\n* Also works for CSS preprocessors (Sass, Stylus, and Less)\n* NPM installed dependencies are excluded by default (can be enabled)\n* All core Node.js modules (assert, path, fs, etc) are excluded\n* Will traverse child dependencies automatically\n\nRead the [changelog](CHANGELOG.md) for latest changes.\n\n> I've worked with Madge on my free time for the last couple of years and it's been a great experience. It started as an experiment but turned out to be a very useful tool for many developers. I have many ideas for the project and it would definitely be easier to dedicate more time to it with some [financial support](#donations) 🙏\n>\n> Regardless of your contribution, thanks for your support!\n\n## Examples\n\n> Graph generated from madge's own code and dependencies.\n\n<a href=\"http://pahen.github.io/madge/madge.svg\">\n\t<img src=\"http://pahen.github.io/madge/madge.svg\" width=\"888\"/>\n</a>\n\n> A graph with circular dependencies. Blue has dependencies, green has no dependencies, and red has circular dependencies.\n\n<a href=\"http://pahen.github.io/madge/simple.svg\">\n\t<img src=\"http://pahen.github.io/madge/simple.svg\" width=\"300\"/>\n</a>\n\n## See it in action\n\n<a href=\"https://asciinema.org/a/l9tM7lIraCpmzH0rdWw2KLrMc?autoplay=1\">\n\t<img src=\"https://asciinema.org/a/l9tM7lIraCpmzH0rdWw2KLrMc.png\" width=\"590\"/>\n</a>\n\n# Installation\n\n```sh\nnpm -g install madge\n```\n\n## Graphviz (optional)\n\n> [Graphviz](http://www.graphviz.org/) is only required if you want to generate visual graphs (e.g. in SVG or DOT format).\n\n### Mac OS X\n\n```sh\nbrew install graphviz || port install graphviz\n```\n\n### Ubuntu\n\n```sh\napt-get install graphviz\n```\n\n# API\n\n## madge(path: string|array|object, config: object)\n\n> `path` is a single file or directory, or an array of files/directories to read. A predefined tree can also be passed in as an object.\n\n> `config` is optional and should be the [configuration](#configuration) to use.\n\n> Returns a `Promise` resolved with the Madge instance object.\n\n## Functions\n\n#### .obj()\n\n> Returns an `Object` with all dependencies.\n\n```javascript\nconst madge = require('madge');\n\nmadge('path/to/app.js').then((res) => {\n\tconsole.log(res.obj());\n});\n```\n\n#### .warnings()\n\n> Returns an `Object` of warnings.\n\n```javascript\nconst madge = require('madge');\n\nmadge('path/to/app.js').then((res) => {\n\tconsole.log(res.warnings());\n});\n```\n\n#### .circular()\n\n> Returns an `Array` of all modules that has circular dependencies.\n\n```javascript\nconst madge = require('madge');\n\nmadge('path/to/app.js').then((res) => {\n\tconsole.log(res.circular());\n});\n```\n\n#### .circularGraph()\n\n> Returns an `Object` with only circular dependencies.\n\n```javascript\nconst madge = require('madge');\n\nmadge('path/to/app.js').then((res) => {\n\tconsole.log(res.circularGraph());\n});\n```\n\n#### .depends()\n\n> Returns an `Array` of all modules that depend on a given module.\n\n```javascript\nconst madge = require('madge');\n\nmadge('path/to/app.js').then((res) => {\n\tconsole.log(res.depends('lib/log.js'));\n});\n```\n\n#### .orphans()\n\n> Return an `Array` of all modules that no one is depending on.\n\n```javascript\nconst madge = require('madge');\n\nmadge('path/to/app.js').then((res) => {\n\tconsole.log(res.orphans());\n});\n```\n\n#### .leaves()\n\n> Return an `Array` of all modules that have no dependencies.\n\n```javascript\nconst madge = require('madge');\n\nmadge('path/to/app.js').then((res) => {\n\tconsole.log(res.leaves());\n});\n```\n\n#### .dot([circularOnly: boolean])\n\n> Returns a `Promise` resolved with a DOT representation of the module dependency graph. Set `circularOnly` to only include circular dependencies.\n\n```javascript\nconst madge = require('madge');\n\nmadge('path/to/app.js')\n\t.then((res) => res.dot())\n\t.then((output) => {\n\t\tconsole.log(output);\n\t});\n```\n\n#### .image(imagePath: string, [circularOnly: boolean])\n\n> Write the graph as an image to the given image path. Set `circularOnly` to only include circular dependencies. The [image format](http://www.graphviz.org/content/output-formats) to use is determined from the file extension. Returns a `Promise` resolved with a full path to the written image.\n\n```javascript\nconst madge = require('madge');\n\nmadge('path/to/app.js')\n\t.then((res) => res.image('path/to/image.svg'))\n\t.then((writtenImagePath) => {\n\t\tconsole.log('Image written to ' + writtenImagePath);\n\t});\n```\n\n#### .svg()\n\n> Return a `Promise` resolved with the XML SVG representation of the dependency graph as a `Buffer`.\n\n```javascript\nconst madge = require('madge');\n\nmadge('path/to/app.js')\n\t.then((res) => res.svg())\n\t.then((output) => {\n\t\tconsole.log(output.toString());\n\t});\n```\n\n# Configuration\n\nProperty | Type | Default | Description\n--- | --- | --- | ---\n`baseDir` | String | null | Base directory to use instead of the default\n`includeNpm` | Boolean | false | If shallow NPM modules should be included\n`fileExtensions` | Array | ['js'] | Valid file extensions used to find files in directories\n`excludeRegExp` | Array | false | An array of RegExp for excluding modules\n`requireConfig` | String | null | RequireJS config for resolving aliased modules\n`webpackConfig` | String | null | Webpack config for resolving aliased modules\n`tsConfig` | String\\|Object | null | TypeScript config for resolving aliased modules - Either a path to a tsconfig file or an object containing the config\n`layout` | String | dot | Layout to use in the graph\n`rankdir` | String | LR | Sets the [direction](https://graphviz.gitlab.io/_pages/doc/info/attrs.html#d:rankdir) of the graph layout\n`fontName` | String | Arial | Font name to use in the graph\n`fontSize` | String | 14px | Font size to use in the graph\n`backgroundColor` | String | #000000 | Background color for the graph\n`nodeShape` | String | box | A string specifying the [shape](https://graphviz.gitlab.io/_pages/doc/info/attrs.html#k:shape) of a node in the graph\n`nodeStyle` | String | rounded | A string specifying the [style](https://graphviz.gitlab.io/_pages/doc/info/attrs.html#k:style) of a node in the graph\n`nodeColor` | String | #c6c5fe | Default node color to use in the graph\n`noDependencyColor` | String | #cfffac | Color to use for nodes with no dependencies\n`cyclicNodeColor` | String | #ff6c60 | Color to use for circular dependencies\n`edgeColor` | String | #757575 | Edge color to use in the graph\n`graphVizOptions` | Object | false | Custom Graphviz [options](https://graphviz.gitlab.io/_pages/doc/info/attrs.html)\n`graphVizPath` | String | null | Custom Graphviz path\n`detectiveOptions` | Object | false | Custom `detective` options for [dependency-tree](https://github.com/dependents/node-dependency-tree) and [precinct](https://github.com/dependents/node-precinct#usage)\n`dependencyFilter` | Function | false | Function called with a dependency filepath (exclude substree by returning false)\n\nYou can use configuration file either in `.madgerc` in your project or home folder or directly in `package.json`. Look [here](https://github.com/dominictarr/rc#standards) for alternative locations for the file.\n\n> .madgerc\n\n```json\n{\n\t\"fontSize\": \"10px\",\n\t\"graphVizOptions\": {\n\t\t\"G\": {\n\t\t\t\"rankdir\": \"LR\"\n\t\t}\n\t}\n}\n```\n\n> package.json\n```json\n{\n\t\"name\": \"foo\",\n\t\"version\": \"0.0.1\",\n\t...\n\t\"madge\": {\n\t\t\"fontSize\": \"10px\",\n\t\t\"graphVizOptions\": {\n\t\t\t\"G\": {\n\t\t\t\t\"rankdir\": \"LR\"\n\t\t\t}\n\t\t}\n\t}\n}\n```\n\n# CLI\n\n## Examples\n\n> List dependencies from a single file\n\n```sh\nmadge path/src/app.js\n```\n\n> List dependencies from multiple files\n\n```sh\nmadge path/src/foo.js path/src/bar.js\n```\n\n> List dependencies from all *.js files found in a directory\n\n```sh\nmadge path/src\n```\n\n> List dependencies from multiple directories\n\n```sh\nmadge path/src/foo path/src/bar\n```\n\n> List dependencies from all *.js and *.jsx files found in a directory\n\n```sh\nmadge --extensions js,jsx path/src\n```\n\n> Finding circular dependencies\n\n```sh\nmadge --circular path/src/app.js\n```\n\n> Show modules that depends on a given module\n\n```sh\nmadge --depends wheels.js path/src/app.js\n```\n\n> Show modules that no one is depending on\n\n```sh\nmadge --orphans path/src/\n```\n\n> Show modules that have no dependencies\n\n```sh\nmadge --leaves path/src/\n```\n\n> Excluding modules\n\n```sh\nmadge --exclude '^(foo|bar)\\.js$' path/src/app.js\n```\n\n> Save graph as a SVG image (requires [Graphviz](#graphviz-optional))\n\n```sh\nmadge --image graph.svg path/src/app.js\n```\n\n> Save graph with only circular dependencies\n\n```sh\nmadge --circular --image graph.svg path/src/app.js\n```\n\n> Save graph as a [DOT](http://en.wikipedia.org/wiki/DOT_language) file for further processing (requires [Graphviz](#graphviz-optional))\n\n```sh\nmadge --dot path/src/app.js > graph.gv\n```\n\n> Using pipe to transform tree (this example will uppercase all paths)\n\n```sh\nmadge --json path/src/app.js | tr '[a-z]' '[A-Z]' | madge --stdin\n```\n\n# Debugging\n\n> To enable debugging output if you encounter problems, run madge with the `--debug` option then throw the result in a gist when creating issues on GitHub.\n\n```sh\nmadge --debug path/src/app.js\n```\n\n# Running tests\n\n```sh\nnpm install\nnpm test\n```\n\n# FAQ\n\n## Missing dependencies?\n\nIt could happen that the files you're not seeing have been skipped due to errors or that they can't be resolved. Run madge with the `--warning` option to see skipped files. If you need even more info run with the `--debug` option.\n\n## Using both Javascript and Typescript in your project?\n\nMadge uses [dependency-tree](https://www.npmjs.com/package/dependency-tree) which uses [filing-cabinet](https://www.npmjs.com/package/filing-cabinet) to resolve modules. However it requires configurations for each file type (js/jsx) and (ts/tsx). So provide both `webpackConfig` and `tsConfig` options to madge.\n\n## Using mixed import syntax in the same file?\n\nOnly one syntax is used by default. You can use both though if you're willing to take the degraded performance. Put this in your madge config to enable mixed imports.\n\nFor ES6 + CommonJS:\n```json\n{\n\t\"detectiveOptions\": {\n\t\t\"es6\": {\n\t\t\t\"mixedImports\": true\n\t\t}\n\t}\n}\n```\n\nFor TypeScript + CommonJS:\n```json\n{\n\t\"detectiveOptions\": {\n\t\t\"ts\": {\n\t\t\t\"mixedImports\": true\n\t\t}\n\t}\n}\n```\n\n## How to ignore `import type` statements in ES6 + Flow?\n\nPut this in your madge config.\n\n```json\n{\n\t\"detectiveOptions\": {\n\t\t\"es6\": {\n\t\t\t\"skipTypeImports\": true\n\t\t}\n\t}\n}\n```\n\n## How to ignore `import` in type annotations in TypeScript?\n\nPut this in your madge config.\n\n```json\n{\n\t\"detectiveOptions\": {\n\t\t\"ts\": {\n\t\t\t\"skipTypeImports\": true\n\t\t}\n\t}\n}\n```\n\n## Mixing TypesScript and Javascript imports?\n\nEnsure you have this in your `.tsconfig` file.\n\n```json\n{\n\t\"compilerOptions\": {\n\t\t\"module\": \"commonjs\",\n\t\t\"allowJs\": true\n\t}\n}\n```\n\n## What's the \"Error: write EPIPE\" when exporting graph to image?\n\nEnsure you have [installed Graphviz](#graphviz-optional). If you're running Windows, note that Graphviz is not added to the `PATH` variable during install. You should add the folder of `gvpr.exe` (typically `%Graphviz_folder%/bin`) to the `PATH` variable manually.\n\n## How do I fix the \"Graphviz not built with triangulation library\" error when using sfdp layout?\n\nHomebrew doesn't include GTS by default. Fix this by doing:\n\n```sh\nbrew uninstall graphviz\nbrew install gts\nbrew install graphviz\n```\n\n## The image produced by madge is very hard to read, what's wrong?\n\nTry running madge with a different layout, here's a list of the ones you can try:\n\n* **dot**\t\"hierarchical\" or layered drawings of directed graphs. This is the default tool to use if edges have directionality.\n\n* **neato** \"spring model'' layouts.  This is the default tool to use if the graph is not too large (about 100 nodes) and you don't know anything else about it. Neato attempts to\nminimize a global energy function, which is equivalent to statistical multi-dimensional scaling.\n\n* **fdp**\t\"spring model'' layouts similar to those of neato, but does this by reducing forces rather than working with energy.\n\n* **sfdp** multiscale version of fdp for the layout of large graphs.\n\n* **twopi** radial layouts, after Graham Wills 97. Nodes are placed on concentric circles depending their distance from a given root node.\n\n* **circo** circular layout, after Six and Tollis 99, Kauffman and Wiese 02. This is suitable for certain diagrams of multiple cyclic structures, such as certain telecommunications networks.\n\n# Credits\n\n## Contributors\n\nThis project exists thanks to all the people who contribute.\n<a href=\"https://github.com/pahen/madge/graphs/contributors\"><img src=\"https://opencollective.com/madge/contributors.svg?width=890&button=false\" alt=\"Contributors\"/></a>\n\n## Donations ❤️\n\nThanks to the awesome people below for making donations! 🙏[[Donate](https://paypal.me/pahen)]\n\n<p>\n  <a href=\"https://github.com/BeroBurny\" target=\"_blank\">\n    <div><b>Bernard Stojanović</b> (24 Mars, 2021)</div>\n    <img src=\"https://github.com/BeroBurny.png\" width=\"64\"/>\n  </a>\n</p>\n\n<p>\n  <a href=\"https://github.com/olejorgenb\" target=\"_blank\">\n    <div><b>Ole Jørgen Brønner</b> (Oct 8, 2020)</div>\n    <img src=\"https://github.com/olejorgenb.png\" width=\"64\"/>\n  </a>\n</p>\n\n<p>\n  <a href=\"https://github.com/pubkey/rxdb\" target=\"_blank\">\n    <div><b>RxDB</b> (Apr 1, 2020)</div>\n    <img src=\"https://cdn.rawgit.com/pubkey/rxdb/ba7c9b80/docs/files/logo/logo_text.svg\" width=\"128\" style=\"margin: -4px -10px\"/>\n  </a>\n</p>\n\n<p>\n  <a href=\"https://github.com/Ziriax\" target=\"_blank\">\n    <div><b>Peter Verswyvelen</b> (Feb 24, 2020)</div>\n    <img src=\"https://github.com/Ziriax.png\" width=\"64\"/>\n  </a>\n</p>\n\n<p>\n  <a href=\"https://github.com/landonalder\" target=\"_blank\">\n    <div><b>Landon Alder</b> (Mar 19, 2019)</div>\n    <img src=\"https://github.com/landonalder.png\" width=\"64\"/>\n  </a>\n</p>\n\n# License\n\nMIT License"},"npm":{"downloads":[{"from":"2021-08-13T00:00:00.000Z","to":"2021-08-14T00:00:00.000Z","count":25393},{"from":"2021-08-07T00:00:00.000Z","to":"2021-08-14T00:00:00.000Z","count":164515},{"from":"2021-07-15T00:00:00.000Z","to":"2021-08-14T00:00:00.000Z","count":687911},{"from":"2021-05-16T00:00:00.000Z","to":"2021-08-14T00:00:00.000Z","count":2113821},{"from":"2021-02-15T00:00:00.000Z","to":"2021-08-14T00:00:00.000Z","count":3986591},{"from":"2020-08-14T00:00:00.000Z","to":"2021-08-14T00:00:00.000Z","count":7010284}],"dependentsCount":84,"starsCount":29},"github":{"starsCount":5251,"forksCount":248,"subscribersCount":53,"issues":{"count":290,"openCount":45,"distribution":{"3600":27,"10800":8,"32400":13,"97200":24,"291600":31,"874800":29,"2624400":23,"7873200":27,"23619600":39,"70858800":53,"212576400":16},"isDisabled":false},"contributors":[{"username":"trevorah","commitsCount":1},{"username":"Havunen","commitsCount":1},{"username":"nadejdashed","commitsCount":1},{"username":"wayofthefuture","commitsCount":1},{"username":"zekth","commitsCount":2},{"username":"mwhite","commitsCount":2},{"username":"OliverJAsh","commitsCount":1},{"username":"NikhilVerma","commitsCount":1},{"username":"paulirish","commitsCount":2},{"username":"avahe-kellenberger","commitsCount":1},{"username":"waldyrious","commitsCount":1},{"username":"pahen","commitsCount":316},{"username":"realityking","commitsCount":18},{"username":"mrjoelkemp","commitsCount":2},{"username":"mdarse","commitsCount":1},{"username":"danielbaak","commitsCount":1},{"username":"russaa","commitsCount":2},{"username":"customcommander","commitsCount":1},{"username":"olalonde","commitsCount":1},{"username":"lleaff","commitsCount":2},{"username":"blowery","commitsCount":1},{"username":"ccoenen","commitsCount":1},{"username":"gingermusketeer","commitsCount":1},{"username":"FauxFaux","commitsCount":1},{"username":"JonDum","commitsCount":1},{"username":"osamie","commitsCount":1},{"username":"RusinovAnton","commitsCount":1},{"username":"hulkish","commitsCount":1},{"username":"wheresrhys","commitsCount":1},{"username":"marclaval","commitsCount":1},{"username":"neelance","commitsCount":1},{"username":"joebowbeer","commitsCount":1},{"username":"meister","commitsCount":3},{"username":"BPScott","commitsCount":1},{"username":"Klaasvaak","commitsCount":1},{"username":"warpdesign","commitsCount":1},{"username":"fizker","commitsCount":3},{"username":"danez","commitsCount":1},{"username":"SethDavenport","commitsCount":1},{"username":"pixeldrew","commitsCount":5},{"username":"rmi7","commitsCount":1}],"commits":[{"from":"2021-08-07T00:00:00.000Z","to":"2021-08-14T00:00:00.000Z","count":0},{"from":"2021-07-15T00:00:00.000Z","to":"2021-08-14T00:00:00.000Z","count":0},{"from":"2021-05-16T00:00:00.000Z","to":"2021-08-14T00:00:00.000Z","count":5},{"from":"2021-02-15T00:00:00.000Z","to":"2021-08-14T00:00:00.000Z","count":11},{"from":"2020-08-14T00:00:00.000Z","to":"2021-08-14T00:00:00.000Z","count":25}]},"source":{"files":{"readmeSize":15020,"testsSize":24244,"hasChangelog":true},"badges":[{"urls":{"original":"http://img.shields.io/travis/pahen/madge/master.svg?style=flat-square","service":"https://api.travis-ci.org/pahen/madge.svg?branch=master","shields":"https://img.shields.io/travis/pahen/madge/master.svg","content":"https://img.shields.io/travis/pahen/madge/master.json"},"info":{"service":"travis","type":"build","modifiers":{"branch":"master"}}},{"urls":{"original":"http://img.shields.io/david/pahen/madge.svg?style=flat-square","service":"https://david-dm.org/pahen/madge.svg","shields":"https://img.shields.io/david/pahen/madge.svg","content":"https://img.shields.io/david/pahen/madge.json"},"info":{"service":"david","type":"dependencies","modifiers":{"statusType":"normal"}}},{"urls":{"original":"http://img.shields.io/david/dev/pahen/madge.svg?style=flat-square","service":"https://david-dm.org/pahen/madge/dev-status.svg","shields":"https://img.shields.io/david/dev/pahen/madge.svg","content":"https://img.shields.io/david/dev/pahen/madge.json"},"info":{"service":"david","type":"dependencies","modifiers":{"statusType":"dev"}}},{"urls":{"original":"http://img.shields.io/npm/dm/madge.svg?style=flat-square","shields":"https://img.shields.io/npm/dm/madge.svg","content":"https://img.shields.io/npm/dm/madge.json"},"info":{"service":"npm","type":"downloads","modifiers":{"type":"dm"}}}],"linters":["editorconfig","eslint"],"outdatedDependencies":{"commander":{"required":"^7.2.0","stable":"8.1.0","latest":"8.1.0"},"typescript":{"required":"^3.9.5","stable":"4.0.5","latest":"4.2.0-dev.20201114"}}}},"evaluation":{"quality":{"carefulness":0.9199999999999999,"tests":0.6,"health":0.8181818181818181,"branding":0.6},"popularity":{"communityInterest":5622,"downloadsCount":704607,"downloadsAcceleration":1666.3948439878232,"dependentsCount":84},"maintenance":{"releasesFrequency":0.9446061643835617,"commitsFrequency":0.7117979452054795,"openIssues":1,"issuesDistribution":0}},"score":{"final":0.6537306656639783,"detail":{"quality":0.9313626735629329,"popularity":0.4032421089584014,"maintenance":0.6662489298847369}}}